discord_fate_bot/__init__.py
discord_fate_bot/bot.py
discord_fate_bot/config.py
discord_fate_bot/console_script.py
discord_fate_bot/database.py
discord_fate_bot/dice.py
discord_fate_bot/extensions/__init__.py
discord_fate_bot/extensions/error_handling.py
discord_fate_bot/extensions/log_invite_url.py
discord_fate_bot/extensions/rolling.py
discord_fate_bot/extensions/scene_management.py
discord_fate_bot/logging.ini
discord_fate_bot/logging.py
discord_fate_bot/scenes.py
discord_fate_bot/util.py
discord_fate_bot-0.4.0.dist-info/entry_points.txt
discord_fate_bot-0.4.0.dist-info/LICENSE.txt
discord_fate_bot-0.4.0.dist-info/WHEEL
discord_fate_bot-0.4.0.dist-info/METADATA
discord_fate_bot-0.4.0.dist-info/RECORD
