Metadata-Version: 2.1
Name: discord-fate-bot
Version: 0.4.0
Summary: Discord bot to help run a FATE campaign
Home-page: https://github.com/chrisbouchard/discord-fate-bot
License: MIT
Author: Chris Bouchard
Author-email: chris@upliftinglemma.net
Requires-Python: >=3.7,<4.0
Classifier: License :: OSI Approved :: MIT License
Classifier: Operating System :: OS Independent
Classifier: Programming Language :: Python :: 3
Classifier: Programming Language :: Python :: 3.7
Classifier: Programming Language :: Python :: 3.8
Classifier: Topic :: Communications :: Chat
Classifier: Topic :: Games/Entertainment :: Role-Playing
Requires-Dist: aiofiles (>=0.4.0,<0.5.0)
Requires-Dist: aiorun (>=2020.2.1,<2021.0.0)
Requires-Dist: discord.py (>=1.3.2,<2.0.0)
Requires-Dist: environ-config (>=20.1.0,<21.0.0)
Requires-Dist: mashumaro (>=1.12,<2.0)
Requires-Dist: motor (>=2.1.0,<3.0.0)
Project-URL: Repository, https://github.com/chrisbouchard/discord-fate-bot
